pyometrics/__init__.py
pyometrics/gmm_biometrics.py
pyometrics-0.1.1.dist-info/licenses/LICENSE
pyometrics-0.1.1.dist-info/METADATA
pyometrics-0.1.1.dist-info/WHEEL
pyometrics-0.1.1.dist-info/top_level.txt
pyometrics-0.1.1.dist-info/RECORD
