Metadata-Version: 2.4
Name: pyometrics
Version: 0.1.1
Summary: A library for creating and comparing voice biometrics using GMM models.
Author: Vedant Pramod Kadam
Author-email: risingved.rv@gmail.com
Classifier: Programming Language :: Python :: 3
Classifier: Operating System :: OS Independent
Requires-Python: >=3.6
License-File: LICENSE
Requires-Dist: librosa
Requires-Dist: numpy
Requires-Dist: scikit-learn
Dynamic: author
Dynamic: author-email
Dynamic: classifier
Dynamic: description
Dynamic: description-content-type
Dynamic: license-file
Dynamic: requires-dist
Dynamic: requires-python
Dynamic: summary
